PolibaseService/__init__.py
PolibaseService/__main__.py
PolibaseService/api.py
PolibaseService/api_test.py
PolibaseService/collection.py
PolibaseService/const.py
PolibaseService/create_all_barcodes.py
PolibaseService/service.py
pih_plb-1.21.dist-info/METADATA
pih_plb-1.21.dist-info/WHEEL
pih_plb-1.21.dist-info/entry_points.txt
pih_plb-1.21.dist-info/top_level.txt
pih_plb-1.21.dist-info/RECORD
