Metadata-Version: 2.1
Name: pih-plb
Version: 1.21
Summary: PIH Polibase service package
Home-page: https://pacifichosp.com/
Author: Nikita Karachentsev
Author-email: it@pacifichosp.com
License: MIT
Requires-Dist: ipih
Requires-Dist: oracledb
